{"customer_id": "C3", "basket": [{"product_id": "P32", "price": 1978}], "date_of_purchase": "2018-12-03 04:08:00"}
{"customer_id": "C12", "basket": [{"product_id": "P64", "price": 703}, {"product_id": "P61", "price": 1616}, {"product_id": "P62", "price": 608}], "date_of_purchase": "2018-12-03 10:43:00"}
{"customer_id": "C24", "basket": [{"product_id": "P04", "price": 331}, {"product_id": "P11", "price": 1056}, {"product_id": "P07", "price": 220}], "date_of_purchase": "2018-12-03 18:06:00"}
{"customer_id": "C30", "basket": [{"product_id": "P46", "price": 866}, {"product_id": "P57", "price": 761}, {"product_id": "P55", "price": 743}], "date_of_purchase": "2018-12-03 23:00:00"}
{"customer_id": "C34", "basket": [{"product_id": "P43", "price": 881}], "date_of_purchase": "2018-12-03 17:26:00"}
{"customer_id": "C40", "basket": [{"product_id": "P12", "price": 1441}], "date_of_purchase": "2018-12-03 23:10:00"}
{"customer_id": "C47", "basket": [{"product_id": "P03", "price": 1551}, {"product_id": "P12", "price": 272}, {"product_id": "P03", "price": 1466}], "date_of_purchase": "2018-12-03 21:19:00"}
{"customer_id": "C55", "basket": [{"product_id": "P40", "price": 1964}, {"product_id": "P40", "price": 1088}], "date_of_purchase": "2018-12-03 05:23:00"}
{"customer_id": "C57", "basket": [{"product_id": "P33", "price": 150}, {"product_id": "P22", "price": 1087}, {"product_id": "P28", "price": 1401}], "date_of_purchase": "2018-12-03 02:57:00"}
{"customer_id": "C63", "basket": [{"product_id": "P64", "price": 255}, {"product_id": "P63", "price": 152}, {"product_id": "P63", "price": 1678}], "date_of_purchase": "2018-12-03 16:56:00"}
{"customer_id": "C65", "basket": [{"product_id": "P39", "price": 1674}, {"product_id": "P38", "price": 998}, {"product_id": "P36", "price": 337}], "date_of_purchase": "2018-12-03 09:37:00"}
{"customer_id": "C75", "basket": [{"product_id": "P35", "price": 1403}], "date_of_purchase": "2018-12-03 06:06:00"}
{"customer_id": "C78", "basket": [{"product_id": "P38", "price": 1263}, {"product_id": "P35", "price": 166}], "date_of_purchase": "2018-12-03 21:50:00"}
{"customer_id": "C79", "basket": [{"product_id": "P28", "price": 647}], "date_of_purchase": "2018-12-03 14:30:00"}
{"customer_id": "C82", "basket": [{"product_id": "P54", "price": 483}], "date_of_purchase": "2018-12-03 04:40:00"}
{"customer_id": "C87", "basket": [{"product_id": "P47", "price": 843}, {"product_id": "P41", "price": 1002}, {"product_id": "P48", "price": 121}], "date_of_purchase": "2018-12-03 05:58:00"}
{"customer_id": "C94", "basket": [{"product_id": "P63", "price": 1629}], "date_of_purchase": "2018-12-03 04:22:00"}
{"customer_id": "C104", "basket": [{"product_id": "P35", "price": 1963}], "date_of_purchase": "2018-12-03 06:28:00"}
{"customer_id": "C112", "basket": [{"product_id": "P53", "price": 1044}, {"product_id": "P47", "price": 769}], "date_of_purchase": "2018-12-03 09:18:00"}
{"customer_id": "C116", "basket": [{"product_id": "P01", "price": 99}, {"product_id": "P11", "price": 1346}], "date_of_purchase": "2018-12-03 06:12:00"}
{"customer_id": "C122", "basket": [{"product_id": "P42", "price": 1093}], "date_of_purchase": "2018-12-03 15:39:00"}
{"customer_id": "C124", "basket": [{"product_id": "P64", "price": 1031}, {"product_id": "P63", "price": 437}, {"product_id": "P61", "price": 752}], "date_of_purchase": "2018-12-03 04:29:00"}
{"customer_id": "C127", "basket": [{"product_id": "P10", "price": 247}, {"product_id": "P06", "price": 870}], "date_of_purchase": "2018-12-03 03:55:00"}
{"customer_id": "C129", "basket": [{"product_id": "P47", "price": 234}, {"product_id": "P48", "price": 223}], "date_of_purchase": "2018-12-03 20:12:00"}
{"customer_id": "C137", "basket": [{"product_id": "P62", "price": 414}, {"product_id": "P64", "price": 488}, {"product_id": "P64", "price": 126}], "date_of_purchase": "2018-12-03 06:17:00"}
